chaosterraform/__init__.py
chaosterraform/control.py
chaosterraform/driver.py
chaostoolkit_terraform-0.0.9.dist-info/LICENSE
chaostoolkit_terraform-0.0.9.dist-info/METADATA
chaostoolkit_terraform-0.0.9.dist-info/WHEEL
chaostoolkit_terraform-0.0.9.dist-info/top_level.txt
chaostoolkit_terraform-0.0.9.dist-info/RECORD
