Metadata-Version: 2.1
Name: chaostoolkit-terraform
Version: 0.0.9
Summary: A Chaos Toolkit module to deploy terraform stacks
Author: Manuel Castellin
Project-URL: homepage, https://github.com/mcastellin/chaostoolkit-terraform
License-File: LICENSE
Requires-Dist: chaostoolkit
Requires-Dist: chaostoolkit-lib
